eve_azure_ad_auth/__init__.py
eve_azure_ad_auth/__version__.py
eve_azure_ad_auth/auth.py
eve_azure_ad_auth/jwksutils.py
eve_azure_ad_auth/verifier.py
Eve_Azure_Auth-0.3.0.dist-info/METADATA
Eve_Azure_Auth-0.3.0.dist-info/WHEEL
Eve_Azure_Auth-0.3.0.dist-info/top_level.txt
Eve_Azure_Auth-0.3.0.dist-info/RECORD
