Metadata-Version: 2.1
Name: Eve-Azure-Auth
Version: 0.3.0
Summary: UNKNOWN
Home-page: https://github.com/ateliedocodigo/eve-azure-auth
Author: LuisComS
Author-email: luiscoms@ateliedocodigo.com.br
License: UNKNOWN
Platform: UNKNOWN
Requires-Python: >= 3.6
Requires-Dist: PyJWT
Requires-Dist: cachecontrol
Requires-Dist: cryptography
Requires-Dist: eve
